federatedml/__init__.py
federatedml/test.py
federatedml-0.0.2.dist-info/METADATA
federatedml-0.0.2.dist-info/WHEEL
federatedml-0.0.2.dist-info/top_level.txt
federatedml-0.0.2.dist-info/RECORD
